{"Package": "supports-preserve-symlinks-flag", "Used?": "No", "Risk Score": "0.73", "Identified Risks": "Has fewer versions, Has fewer maintainers, Outdated Node version"}
{"Package": "@socket.io/base64-arraybuffer", "Used?": "No", "Risk Score": "0.74", "Identified Risks": "Has fewer versions, Has fewer maintainers, Outdated Node version"}
{"Package": "es-shim-unscopables", "Used?": "No", "Risk Score": "0.84", "Identified Risks": "Has fewer versions, Has fewer maintainers"}
{"Package": "has-property-descriptors", "Used?": "No", "Risk Score": "0.84", "Identified Risks": "Has fewer versions, Has fewer maintainers"}
{"Package": "@colors/colors", "Used?": "No", "Risk Score": "0.69", "Identified Risks": "Has fewer versions, Has fewer maintainers, Outdated Node version"}
